LICENSE
MANIFEST.in
README.md
package.json
setup.py
dash_deck/DeckGL.py
dash_deck/__init__.py
dash_deck/_imports_.py
dash_deck/dash_deck.min.js
dash_deck/dash_deck.min.js.map
dash_deck/metadata.json
dash_deck/package-info.json
dash_deck.egg-info/PKG-INFO
dash_deck.egg-info/SOURCES.txt
dash_deck.egg-info/dependency_links.txt
dash_deck.egg-info/top_level.txt