Metadata-Version: 1.1
Name: dash-deck
Version: 0.0.1
Summary: A Dash Component wrapping deck.gl
Home-page: UNKNOWN
Author: Xing Han Lu <xinghan@plot.ly>
Author-email: UNKNOWN
License: MIT
Platform: UNKNOWN
Classifier: Framework :: Dash
